{
  "date": "2026-01-07",
  "route": "BSB-IGU",
  "stamp": "2025-11-13T04-27-59-819Z",
  "url": "https://www.vaidepromo.com.br/passagens-aereas/pesquisa/BSBIGU260107/1/0/0/Y/",
  "min_price_brl": 515.81,
  "all_prices_brl": [
    515.81,
    552.9,
    651.9,
    722.48,
    726.68,
    731.9,
    775.9,
    789.44,
    842.9,
    874.9,
    898.08,
    964.9,
    1019.46,
    1048.77,
    1095.9,
    1200.08,
    1204.9,
    1234.66,
    1289.9,
    1294.9,
    1398.9,
    1488.9,
    1623.85,
    1745.9,
    1854.9,
    1894.78,
    1964.9,
    2035.9,
    2156.54,
    2160.9,
    2270.9,
    2322.07,
    2329.07,
    2699.91,
    2843.91,
    2999.9,
    3131.89,
    3159.9,
    3298.93,
    3499,
    3641.15
  ]
}