{
  "date": "2025-12-23",
  "route": "UDI-IGU",
  "stamp": "2025-11-12T14-51-38-872Z",
  "url": "https://www.vaidepromo.com.br/passagens-aereas/pesquisa/UDIIGU251223/1/0/0/Y/",
  "min_price_brl": 703.12,
  "all_prices_brl": [
    703.12,
    763.9,
    794.92,
    811.12,
    878.9,
    931.9,
    969.77,
    1013.9,
    1028.31,
    1186.26,
    1335.9,
    1352.59,
    1548.72,
    1796.85,
    1834.9,
    1857.84,
    1895.61,
    2055.9,
    2164.9,
    2274.9,
    2324.9,
    2400.9,
    2419.36,
    2498.45,
    3095.75,
    3626.46,
    3641.15
  ]
}