{
  "date": "2026-01-24",
  "route": "UDI-IGU",
  "stamp": "2025-11-14T14-39-43-630Z",
  "url": "https://www.vaidepromo.com.br/passagens-aereas/pesquisa/UDIIGU260124/1/0/0/Y/",
  "min_price_brl": 594.85,
  "all_prices_brl": [
    594.85,
    602.91,
    603.81,
    657.9,
    669.9,
    737.91,
    738.81,
    819.9,
    829.71,
    838.9,
    863.5,
    903.9,
    921.9,
    930.41,
    951.21,
    1056.9,
    1152.9,
    1294.84,
    1665.9,
    1871.02,
    2016.9,
    2160.9,
    2265.22,
    2295.9,
    3601.66
  ]
}