{
  "date": "2025-12-01",
  "route": "CAC-BSB",
  "stamp": "2025-11-12T23-21-21-931Z",
  "url": "https://www.vaidepromo.com.br/passagens-aereas/pesquisa/CACBSB251201/1/0/0/Y/",
  "min_price_brl": 747.29,
  "all_prices_brl": [
    747.29,
    830.32,
    836.11,
    844.49,
    882.26,
    932.35,
    938.32,
    1011.82,
    1025.06,
    1076.32,
    1108.22,
    1124.9,
    1181.14,
    1213.05,
    1296.49,
    1399.09,
    1618.29,
    1699.21,
    1775.9,
    1842.04,
    1864.69,
    2156.54,
    2640.86,
    2770.46,
    2832.86,
    2962.46,
    3499,
    3641.15
  ]
}